piefish/__init__.py
piefish/info.py
piefish/vec2.py
piefish-0.1.9a0.dist-info/LICENSE.txt
piefish-0.1.9a0.dist-info/METADATA
piefish-0.1.9a0.dist-info/WHEEL
piefish-0.1.9a0.dist-info/top_level.txt
piefish-0.1.9a0.dist-info/zip-safe
piefish-0.1.9a0.dist-info/RECORD
