Metadata-Version: 2.1
Name: piefish
Version: 0.1.9a0
Summary: A 2D graphics API that mimics the Processing API
Home-page: http://github.com/pb2002/PyVis
Author: Pepijn Bakker
Author-email: bakker.pepijn@gmail.com
License: MIT
Platform: UNKNOWN
Requires-Dist: pygame
Requires-Dist: colorama
